model_sqlite/__init__.py
model_sqlite-0.3.dist-info/LICENSE
model_sqlite-0.3.dist-info/METADATA
model_sqlite-0.3.dist-info/WHEEL
model_sqlite-0.3.dist-info/top_level.txt
model_sqlite-0.3.dist-info/RECORD
