Metadata-Version: 2.1
Name: model-sqlite
Version: 0.3
Summary: A model/class based system for interacting with an using SQLite
Author: Dominic Coletti
License: Apache-2.0
Project-URL: Homepage, https://github.com/DominicDJC/model-sqlite
Project-URL: Changelog, https://github.com/DominicDJC/model-sqlite/releases
Project-URL: Issues, https://github.com/DominicDJC/model-sqlite/issues
Project-URL: CI, https://github.com/DominicDJC/model-sqlite/actions
Classifier: License :: OSI Approved :: Apache Software License
Requires-Python: >=3.13
License-File: LICENSE
Provides-Extra: test
Requires-Dist: pytest; extra == "test"
